README.txt
setup.cfg
setup.py
docs/HISTORY.txt
docs/INSTALL.txt
docs/LICENSE.txt
sk/__init__.py
sk.recipe.jython.egg-info/PKG-INFO
sk.recipe.jython.egg-info/SOURCES.txt
sk.recipe.jython.egg-info/dependency_links.txt
sk.recipe.jython.egg-info/entry_points.txt
sk.recipe.jython.egg-info/namespace_packages.txt
sk.recipe.jython.egg-info/requires.txt
sk.recipe.jython.egg-info/top_level.txt
sk.recipe.jython.egg-info/zip-safe
sk/recipe/__init__.py
sk/recipe/jython/README.txt
sk/recipe/jython/__init__.py
sk/recipe/jython/impl.py
sk/recipe/jython/tests.py
sk/recipe/jython/testdata/java
sk/recipe/jython/testdata/jython-fake.jar