Metadata-Version: 1.0
Name: sk.recipe.jython
Version: 0.0.0
Summary: A recipe for Buildout (zc.buildout) to install Jython
Home-page: http://code.google.com/p/buildout-recipes/
Author: Sean Kelly
Author-email: kelly@seankelly.biz
License: BSD
Download-URL: http://code.google.com/p/buildout-recipes/downloads/list
Keywords: buildout jython installation automation
Platform: UNKNOWN
Classifier: Development Status :: 2 - Pre-Alpha
Classifier: Environment :: Console
Classifier: Framework :: Buildout
Classifier: Intended Audience :: Developers
Classifier: License :: OSI Approved :: BSD License
Classifier: Operating System :: OS Independent
Classifier: Programming Language :: Python
Classifier: Topic :: Software Development :: Build Tools
Classifier: Topic :: Software Development :: Libraries :: Java Libraries
